xrsignal/__init__.py
xrsignal/convolution.py
xrsignal/filtering.py
xrsignal/spectral_analysis.py
xrsignal-0.0.2.dist-info/METADATA
xrsignal-0.0.2.dist-info/WHEEL
xrsignal-0.0.2.dist-info/licenses/LICENSE
xrsignal-0.0.2.dist-info/RECORD
