Metadata-Version: 2.3
Name: xrsignal
Version: 0.0.2
Summary: implementing signal processing routines in scipy.signal for distributed computing using xarray as dask
Project-URL: Documentation, https://github.com/unknown/xrsignal#readme
Project-URL: Issues, https://github.com/unknown/xrsignal/issues
Project-URL: Source, https://github.com/unknown/xrsignal
Author-email: John Ragland <jhrag@uw.edu>
License-Expression: MIT
License-File: LICENSE
Keywords: dask,distributed computing,scipy,signal processing,xarray
Classifier: Development Status :: 4 - Beta
Classifier: Programming Language :: Python
Classifier: Programming Language :: Python :: 3.9
Classifier: Programming Language :: Python :: 3.10
Classifier: Programming Language :: Python :: Implementation :: CPython
Classifier: Programming Language :: Python :: Implementation :: PyPy
Requires-Python: >=3.9
Requires-Dist: dask
Requires-Dist: numpy
Requires-Dist: scipy
Requires-Dist: xarray
Provides-Extra: docs
Requires-Dist: furo; extra == 'docs'
Requires-Dist: myst-parser>=0.13; extra == 'docs'
Requires-Dist: sphinx-autodoc-typehints; extra == 'docs'
Requires-Dist: sphinx-copybutton; extra == 'docs'
Requires-Dist: sphinx>=4.0; extra == 'docs'
